Qiber3D/__init__.py
Qiber3D/config.py
Qiber3D/core.py
Qiber3D/extract.py
Qiber3D/figure.py
Qiber3D/filter.py
Qiber3D/helper.py
Qiber3D/io.py
Qiber3D/reconstruct.py
Qiber3D/render.py
Qiber3D-0.7.0.dist-info/LICENSE
Qiber3D-0.7.0.dist-info/METADATA
Qiber3D-0.7.0.dist-info/WHEEL
Qiber3D-0.7.0.dist-info/top_level.txt
Qiber3D-0.7.0.dist-info/zip-safe
Qiber3D-0.7.0.dist-info/RECORD
