Metadata-Version: 2.1
Name: Qiber3D
Version: 0.7.0
Summary: Automated quantification of fibrous networks
Home-page: https://github.com/theia-dev/Qiber3D
Author: Anna Jaeschke; Hagen Eckert
Author-email: 
License: MIT
Download-URL: https://github.com/theia-dev/Qiber3D/archive/v0.7.0.zip
Project-URL: Binder, https://mybinder.org/v2/gh/theia-dev/Qiber3D_jupyter/main?urlpath=git-pull%3Frepo%3Dhttps%253A%252F%252Fgithub.com%252Ftheia-dev%252FQiber3D%26urlpath%3Dtree%252FQiber3D%252Fdocs%252Fjupyter%252Findex.ipynb
Project-URL: Documentation, https://qiber3d.readthedocs.io/
Keywords: Skeleton,Network,Fiber,Reconstruction,Neurons,Vessel,Vascular,confocal,microscopy
Platform: UNKNOWN
Classifier: Development Status :: 4 - Beta
Classifier: Intended Audience :: Science/Research
Classifier: Topic :: Scientific/Engineering :: Bio-Informatics
Classifier: Topic :: Scientific/Engineering :: Information Analysis
Classifier: License :: OSI Approved :: MIT License
Classifier: Operating System :: OS Independent
Classifier: Programming Language :: Python :: 3.7
Classifier: Programming Language :: Python :: 3.8
Classifier: Programming Language :: Python :: 3 :: Only
Requires-Python: ~=3.7
License-File: LICENSE
Requires-Dist: nd2reader (==3.3.0)
Requires-Dist: vedo (==2021.0.5)
Requires-Dist: PIMS (==0.5)
Requires-Dist: tifffile (==2021.10.10)
Requires-Dist: networkx (==2.6.3)
Requires-Dist: matplotlib (==3.4.3)
Requires-Dist: blosc (==1.10.6)
Requires-Dist: openpyxl (==3.0.9)
Requires-Dist: vtk (==9.0.3)
Requires-Dist: kimimaro (==3.0.0)
Requires-Dist: scipy (==1.7.1)
Requires-Dist: tqdm (==4.62.3)
Requires-Dist: scikit-image (==0.18.3)
Requires-Dist: numpy (==1.21.2)
Requires-Dist: Pillow (==8.3.2)
Provides-Extra: kimimaro
Requires-Dist: kimimaro ; extra == 'kimimaro'
